resistant_kafka/__init__.py
resistant_kafka/common_exceptions.py
resistant_kafka/common_schemas.py
resistant_kafka/consumer.py
resistant_kafka/consumer_schemas.py
resistant_kafka/producer.py
resistant_kafka/producer_schemas.py
resistant_kafka-0.8.dist-info/METADATA
resistant_kafka-0.8.dist-info/WHEEL
resistant_kafka-0.8.dist-info/top_level.txt
resistant_kafka-0.8.dist-info/RECORD
